pyxmolpp2-stubs
