Metadata-Version: 1.2
Name: pyxmolpp2-stubs
Version: 0.0.8
Summary: PEP 561 type stubs for pyxmolpp2
Home-page: https://github.com/sizmailov/pyxmolpp2
Maintainer: Sergei Izmailov
Maintainer-email: sergei.a.izmailov@gmail.com
License: UNKNOWN
Platform: UNKNOWN
